py_clob_client_slp/__init__.py
py_clob_client_slp/client.py
py_clob_client_slp/clob_types.py
py_clob_client_slp/config.py
py_clob_client_slp/constants.py
py_clob_client_slp/endpoints.py
py_clob_client_slp/exceptions.py
py_clob_client_slp/signer.py
py_clob_client_slp/utilities.py
py_clob_client_slp/headers/__init__.py
py_clob_client_slp/headers/headers.py
py_clob_client_slp/http_helpers/__init__.py
py_clob_client_slp/http_helpers/helpers.py
py_clob_client_slp/order_builder/__init__.py
py_clob_client_slp/order_builder/builder.py
py_clob_client_slp/order_builder/constants.py
py_clob_client_slp/order_builder/helpers.py
py_clob_client_slp/signing/__init__.py
py_clob_client_slp/signing/eip712.py
py_clob_client_slp/signing/hmac.py
py_clob_client_slp/signing/model.py
py_clob_client_slp-0.30.0.dist-info/licenses/LICENSE
tests/__init__.py
tests/test_utilities.py
tests/headers/__init__.py
tests/headers/test_headers.py
tests/http_helpers/__init__.py
tests/http_helpers/test_helpers.py
tests/order_builder/__init__.py
tests/order_builder/test_builder.py
tests/order_builder/test_helpers.py
tests/signing/__init__.py
tests/signing/test_eip712.py
tests/signing/test_hmac.py
py_clob_client_slp-0.30.0.dist-info/METADATA
py_clob_client_slp-0.30.0.dist-info/WHEEL
py_clob_client_slp-0.30.0.dist-info/top_level.txt
py_clob_client_slp-0.30.0.dist-info/RECORD
