Metadata-Version: 2.4
Name: py_clob_client_slp
Version: 0.30.0
Summary: Python client for the Polymarket CLOB
Home-page: https://github.com/Polymarket/py-clob-client
Author: Polymarket Engineering
Author-email: engineering@polymarket.com
Maintainer: Polymarket Engineering
Maintainer-email: engineering@polymarket.com
Project-URL: Bug Tracker, https://github.com/Polymarket/py-clob-client/issues
Classifier: Programming Language :: Python :: 3
Classifier: License :: OSI Approved :: MIT License
Classifier: Operating System :: OS Independent
Requires-Python: >=3.9.10
License-File: LICENSE
Requires-Dist: eth-account>=0.13.0
Requires-Dist: eth-utils>=4.1.1
Requires-Dist: poly_eip712_structs>=0.0.1
Requires-Dist: py-order-utils>=0.3.2
Requires-Dist: python-dotenv
Requires-Dist: py-builder-signing-sdk>=0.0.2
Requires-Dist: requests
Dynamic: author
Dynamic: author-email
Dynamic: classifier
Dynamic: description
Dynamic: description-content-type
Dynamic: home-page
Dynamic: license-file
Dynamic: maintainer
Dynamic: maintainer-email
Dynamic: project-url
Dynamic: requires-dist
Dynamic: requires-python
Dynamic: summary
